jfscripts/__init__.py
jfscripts/dns_ipv6_prefix.py
jfscripts/extract_pdftext.py
jfscripts/find_dupes_by_size.py
jfscripts/image_into_pdf.py
jfscripts/list_files.py
jfscripts/mac_to_eui64.py
jfscripts/py.typed
jfscripts/utils.py
jfscripts/work_in_progress/csv_to_yaml.py
jfscripts/work_in_progress/find_dupes_by_fuzzy.py
jfscripts-1.1.0.dist-info/entry_points.txt
jfscripts-1.1.0.dist-info/LICENSE
jfscripts-1.1.0.dist-info/WHEEL
jfscripts-1.1.0.dist-info/METADATA
jfscripts-1.1.0.dist-info/RECORD
